netapult_ssh/__init__.py
netapult_ssh-0.0.1.dist-info/METADATA
netapult_ssh-0.0.1.dist-info/WHEEL
netapult_ssh-0.0.1.dist-info/entry_points.txt
netapult_ssh-0.0.1.dist-info/licenses/LICENSE
netapult_ssh-0.0.1.dist-info/RECORD
