Metadata-Version: 2.4
Name: netapult-ssh
Version: 0.0.1
Summary: Plugin for Netapult to support command execution over SSH
Project-URL: Homepage, https://github.com/Jayson-Fong/netapult-ssh
Project-URL: Issues, https://github.com/Jayson-Fong/netapult-ssh/issues
Author-email: Jayson Fong <jayson.fong@gatech.edu>
License: MIT
License-File: LICENSE
Classifier: Development Status :: 1 - Planning
Classifier: License :: OSI Approved :: MIT License
Classifier: Operating System :: OS Independent
Classifier: Programming Language :: Python
Classifier: Programming Language :: Python :: 3.11
Classifier: Programming Language :: Python :: 3.12
Classifier: Programming Language :: Python :: 3.13
Classifier: Topic :: System :: Networking
Classifier: Typing :: Typed
Requires-Python: >=3.11
Requires-Dist: netapult==0.0.1
Requires-Dist: paramiko>=4.0.0
